dbPorter/__init__.py
dbPorter/applier.py
dbPorter/commands.py
dbPorter/db.py
dbPorter/executors.py
dbPorter/main.py
dbPorter/migration_loader.py
dbPorter/models.py
dbPorter/planner.py
dbPorter/utils/__init__.py
dbPorter/utils/constants.py
dbPorter/utils/utils.py
dbporter-0.1.17.dist-info/licenses/LICENSE
dbporter-0.1.17.dist-info/METADATA
dbporter-0.1.17.dist-info/WHEEL
dbporter-0.1.17.dist-info/entry_points.txt
dbporter-0.1.17.dist-info/top_level.txt
dbporter-0.1.17.dist-info/RECORD
