Metadata-Version: 2.4
Name: dbporter
Version: 0.1.17
Summary: A powerful database migration tool with DAG support, automatic rollback, and schema inspection
Home-page: https://github.com/karan-kap00r/dbPorter
Author: Karan Kapoor
Author-email: Karan Kapoor <karankapoor0062@gmail.com>
Maintainer-email: Karan Kapoor <karankapoor0062@gmail.com>
License: MIT
Project-URL: Homepage, https://github.com/karan-kap00r/dbPorter
Project-URL: Documentation, https://github.com/karan-kap00r/dbPorter/blob/main/README.md
Project-URL: Repository, https://github.com/karan-kap00r/dbPorter.git
Project-URL: Bug Tracker, https://github.com/karan-kap00r/dbPorter/issues
Keywords: database,migration,schema,sqlalchemy,yaml,dag,rollback,postgresql,mysql,sqlite,oracle,sqlserver,version-control,database-versioning,schema-management
Platform: any
Classifier: Development Status :: 4 - Beta
Classifier: Intended Audience :: Developers
Classifier: Topic :: Software Development :: Libraries :: Python Modules
Classifier: Topic :: Database
Classifier: Topic :: System :: Archiving :: Backup
Classifier: License :: OSI Approved :: MIT License
Classifier: Programming Language :: Python :: 3
Classifier: Programming Language :: Python :: 3.8
Classifier: Programming Language :: Python :: 3.9
Classifier: Programming Language :: Python :: 3.10
Classifier: Programming Language :: Python :: 3.11
Classifier: Programming Language :: Python :: 3.12
Classifier: Operating System :: OS Independent
Classifier: Environment :: Console
Requires-Python: >=3.8
License-File: LICENSE
Requires-Dist: typer>=0.9.0
Requires-Dist: sqlalchemy>=2.0.0
Requires-Dist: pyyaml>=6.0
Requires-Dist: python-dotenv>=1.0.0
Requires-Dist: tabulate>=0.9.0
Requires-Dist: typing-extensions>=4.0.0
Provides-Extra: postgresql
Requires-Dist: psycopg2-binary>=2.9.0; extra == "postgresql"
Provides-Extra: mysql
Requires-Dist: PyMySQL>=1.0.0; extra == "mysql"
Provides-Extra: sqlserver
Requires-Dist: pyodbc>=4.0.0; extra == "sqlserver"
Provides-Extra: oracle
Requires-Dist: cx-Oracle>=8.0.0; extra == "oracle"
Provides-Extra: dev
Requires-Dist: pytest>=7.0.0; extra == "dev"
Requires-Dist: pytest-cov>=4.0.0; extra == "dev"
Requires-Dist: pytest-mock>=3.10.0; extra == "dev"
Requires-Dist: black>=23.0.0; extra == "dev"
Requires-Dist: flake8>=6.0.0; extra == "dev"
Requires-Dist: mypy>=1.0.0; extra == "dev"
Requires-Dist: isort>=5.12.0; extra == "dev"
Requires-Dist: sphinx>=6.0.0; extra == "dev"
Requires-Dist: sphinx-rtd-theme>=1.2.0; extra == "dev"
Requires-Dist: pre-commit>=3.0.0; extra == "dev"
Requires-Dist: ipython>=8.0.0; extra == "dev"
Requires-Dist: jupyter>=1.0.0; extra == "dev"
Dynamic: author
Dynamic: home-page
Dynamic: license-file
Dynamic: platform
Dynamic: requires-python
